klabmodels/__init__.py
klabmodels/kiwi/__init__.py
klabmodels/kiwi/api.py
klabmodels/kiwi/models.py
klabmodels/kopi/api.py
klabmodels/kopi/models.py
klabmodels/lumina/__init__.py
klabmodels/lumina/api.py
klabmodels/lumina/models.py
klabmodels/pickey/__init__.py
klabmodels/pickey/api.py
klabmodels/pickey/models.py
klabmodels-0.3.35.dist-info/METADATA
klabmodels-0.3.35.dist-info/WHEEL
klabmodels-0.3.35.dist-info/top_level.txt
klabmodels-0.3.35.dist-info/RECORD
