Metadata-Version: 2.1
Name: klabmodels
Version: 0.3.35
Summary: Data models for Kodelab's AI products
Author-email: Maurizio Santamicone <maurizio@kodelab.io>
License: MIT
Project-URL: Homepage, https://github.com/kodelabio/klabmodels.git
Requires-Python: >=3.6
Requires-Dist: pydantic[email]
Requires-Dist: redis-om
Requires-Dist: tiktoken
